CO224 Computer Architecture/Lab_Project/ALUnReg.v
module Register(clk,INaddr,IN,OUT1addr,OUT1,OUT2addr,OUT2);
	input clk;
 input [2:0] INaddr;
 input [7:0] IN;
 input [2:0] OUT1addr;
 output[7:0] OUT1;
 input [2:0] OUT2addr;
 output[7:0] OUT2;

reg [8:0] reg0, reg1, reg2, reg3,reg4,reg5,reg6,reg7;

assign OUT1 = 	OUT1addr == 0 ? reg0 :
				OUT1addr == 1 ? reg1 :
				OUT1addr == 2 ? reg2 :
				OUT1addr == 3 ? reg3 :
				OUT1addr == 4 ? reg4 :
				OUT1addr == 5 ? reg5 :
				OUT1addr == 6 ? reg6 :
				OUT1addr == 7 ? reg7 : 0;


assign OUT2 = 	OUT2addr == 0 ? reg0 :
				OUT2addr == 1 ? reg1 :
				OUT2addr == 2 ? reg2 :
				OUT2addr == 3 ? reg3 :
				OUT2addr == 4 ? reg4 :
				OUT2addr == 5 ? reg5 :
				OUT2addr ==  6? reg6 :
				OUT2addr == 7 ? reg7 : 0;

 
 always @(negedge clk) 
 	begin
 		case(INaddr)
	 		3'b000: reg0=IN;
	 		3'b001: reg1=IN;
	 		3'b010: reg2=IN;
	 		3'b011: reg3=IN;
	 		3'b100: reg4=IN;
	 		3'b101: reg5=IN;
	 		3'b110: reg6=IN;
	 		3'b111: reg7=IN;
	 	endcase
	 end // always @ (negedge clk)
endmodule


module alu(out,DATA1,DATA2,Select);
	input [7:0]DATA1,DATA2;
	input [2:0] Select;
	output [7:0]out;
	reg out;
	always@(DATA1,DATA2,Select)
	begin
		case(Select)
			3'b000: out=DATA1;
			3'b001: out=DATA1+DATA2;
			3'b010: out=DATA1 & DATA2;
			3'b011: out=DATA1| DATA2; 
		//your code here//
		endcase
	end
endmodule


/*module ALUnReg(clk,INaddr,OUT1addr,OUT2addr,Select);
	input [2:0] INaddr, OUT1addr,OUT2addr;
	input clk;
	wire [7:0] IN;
	input[2:0] Select;
	wire [7:0] OUT2,OUT1;
	output [7:0] IN;


	
endmodule	
*/


module stimulus;
	reg clk;
 	reg [2:0] INaddr,OUT1addr,OUT2addr;
 	reg [7:0] IN;
 	wire [7:0] OUT1,OUT2,OUT3,OUT4;
 	reg [2:0] Select;
 	wire[7:0] newIN;

 
	Register r1(clk,INaddr,IN,OUT1addr,OUT1,OUT2addr,OUT2);
	//
    alu a1 (newIN,OUT1,OUT2,Select);

    Register r2(clk,INaddr,newIN,OUT1addr,OUT3,OUT2addr,OUT4);


	//ALUnReg AR1 (clk,INaddr,OUT1addr,OUT2addr,Select);
		initial begin
		$dumpfile("test.vcd");
		$dumpvars(0,stimulus); 
		 #3
		clk=1;
		INaddr=1;
		IN=2;
		#3
		clk=0;


		
		#3
		clk=1;
		INaddr=2;
		IN=4;

		#3
		clk=0;

		#3
		OUT1addr=1;
		OUT2addr=2;
		#3
		clk=0;

		#2
		 Select=3'b001;

		 #2
		 INaddr=3;

		#2
		$monitor("result=%d",newIN);

		#3
		OUT1addr=3;
		OUT2addr=4;
		
		clk=0;
		
		$monitor("INaddre=%d IN=%d newIN=%d OUT1addr=%d OUT1=%d OUT2addr=%d OUT2=%d OUT3=%d OUT4=%d",
			INaddr,IN, newIN,OUT1addr,OUT1,OUT2addr,OUT2,OUT3,OUT4);



		$finish;
		end
endmodule

CO224 Computer Architecture/Lab_Project/test.vcd
$date
	Mon Aug 28 17:19:10 2017
$end
$version
	Icarus Verilog
$end
$timescale
	1s
$end
$scope module stimulus $end
$var wire 8 ! OUT1 [7:0] $end
$var wire 8 " OUT2 [7:0] $end
$var wire 8 # OUT3 [7:0] $end
$var wire 8 $ OUT4 [7:0] $end
$var wire 8 % newIN [7:0] $end
$var reg 8 & IN [7:0] $end
$var reg 3 ' INaddr [2:0] $end
$var reg 3 ( OUT1addr [2:0] $end
$var reg 3 ) OUT2addr [2:0] $end
$var reg 3 * Select [2:0] $end
$var reg 1 + clk $end
$scope module r1 $end
$var wire 8 , IN [7:0] $end
$var wire 3 - INaddr [2:0] $end
$var wire 8 . OUT1 [7:0] $end
$var wire 3 / OUT1addr [2:0] $end
$var wire 8 0 OUT2 [7:0] $end
$var wire 3 1 OUT2addr [2:0] $end
$var wire 1 2 clk $end
$var reg 9 3 reg0 [8:0] $end
$var reg 9 4 reg1 [8:0] $end
$var reg 9 5 reg2 [8:0] $end
$var reg 9 6 reg3 [8:0] $end
$var reg 9 7 reg4 [8:0] $end
$var reg 9 8 reg5 [8:0] $end
$var reg 9 9 reg6 [8:0] $end
$var reg 9 : reg7 [8:0] $end
$upscope $end
$scope module a1 $end
$var wire 8 ; DATA1 [7:0] $end
$var wire 8 < DATA2 [7:0] $end
$var wire 3 = Select [2:0] $end
$var reg 8 > out [7:0] $end
$upscope $end
$scope module r2 $end
$var wire 8 ? IN [7:0] $end
$var wire 3 @ INaddr [2:0] $end
$var wire 8 A OUT1 [7:0] $end
$var wire 3 B OUT1addr [2:0] $end
$var wire 8 C OUT2 [7:0] $end
$var wire 3 D OUT2addr [2:0] $end
$var wire 1 2 clk $end
$var reg 9 E reg0 [8:0] $end
$var reg 9 F reg1 [8:0] $end
$var reg 9 G reg2 [8:0] $end
$var reg 9 H reg3 [8:0] $end
$var reg 9 I reg4 [8:0] $end
$var reg 9 J reg5 [8:0] $end
$var reg 9 K reg6 [8:0] $end
$var reg 9 L reg7 [8:0] $end
$upscope $end
$upscope $end
$enddefinitions $end
#0
$dumpvars
bx L
bx K
bx J
bx I
bx H
bx G
bx F
bx E
bx D
bx C
bx B
bx A
bx @
bx ?
bx >
bx =
bx <
bx ;
bx :
bx 9
bx 8
bx 7
bx 6
bx 5
bx 4
bx 3
x2
bx 1
bx 0
bx /
bx .
bx -
bx ,
x+
bx *
bx )
bx (
bx '
bx &
bx %
bx $
bx #
bx "
bx !
$end
#3
b10 &
b10 ,
b1 '
b1 -
b1 @
1+
12
#6
b10 4
b0xxxxxxxx F
0+
02
#9
b100 &
b100 ,
b10 '
b10 -
b10 @
1+
12
#12
b0xxxxxxxx G
b100 5
0+
02
#15
b100 "
b100 0
b100 <
b10 !
b10 .
b10 ;
b10 )
b10 1
b10 D
b1 (
b1 /
b1 B
#20
b110 >
b110 %
b110 ?
b1 *
b1 =
#22
b11 '
b11 -
b11 @
#24
bx "
bx 0
bx <
bx $
bx C
bx >
bx %
bx ?
bx !
bx .
bx ;
bx #
bx A
b100 )
b100 1
b100 D
b11 (
b11 /
b11 B
